<?xml version="1.0" encoding="UTF-8" ?>

<!-- 
 * tiles_es.xml
 *
 * Copyright (C) 2018 Universidad de Sevilla
 * 
 * The use of this project is hereby constrained to the conditions of the 
 * TDG Licence, a copy of which you may download from 
 * http://www.tdg-seville.info/License.html
 -->

<!DOCTYPE tiles-definitions PUBLIC
       "-//Apache Software Foundation//DTD Tiles Configuration 2.0//EN"
       "http://tiles.apache.org/dtds/tiles-config_2_0.dtd">
      
<tiles-definitions>

	<definition name="administrator/administrator/create" extends="master.page">
		<put-attribute name="title" value="Registro" />
		<put-attribute name="body" value="/views/administrator/register.jsp" />
	</definition>
	
	<definition name="administrator/administrator/edit" extends="master.page">
		<put-attribute name="title" value="Editar informacion personal" />
		<put-attribute name="body" value="/views/administrator/edit.jsp" />
	</definition>

	<definition name="administrator/actorList" extends="master.page">
		<put-attribute name="title" value="Lista de actores" />
		<put-attribute name="body" value="/views/administrator/actorList.jsp" />
	</definition>

	<definition name="administrator/actorList/showActor" extends="master.page">
		<put-attribute name="title" value="Mostrar actor" />
		<put-attribute name="body" value="/views/administrator/showActor.jsp" />
	</definition>

	<definition name="administrator/dashboard" extends="master.page">
		<put-attribute name="title" value="Tabla de estadisticas" />
		<put-attribute name="body" value="/views/administrator/dashboard.jsp" />
	</definition>

	<definition name="administrator/auditor/create" extends="master.page">
		<put-attribute name="title" value="Registrar oyente" />
		<put-attribute name="body" value="/views/administrator/registerAuditor.jsp" />
	</definition>
	
</tiles-definitions>